FastFlask/click/__init__.py
FastFlask/click/_compat.py
FastFlask/click/_termui_impl.py
FastFlask/click/_textwrap.py
FastFlask/click/_unicodefun.py
FastFlask/click/_winconsole.py
FastFlask/click/core.py
FastFlask/click/decorators.py
FastFlask/click/exceptions.py
FastFlask/click/formatting.py
FastFlask/click/globals.py
FastFlask/click/parser.py
FastFlask/click/shell_completion.py
FastFlask/click/termui.py
FastFlask/click/testing.py
FastFlask/click/types.py
FastFlask/click/utils.py
FastFlask/colorama/__init__.py
FastFlask/colorama/ansi.py
FastFlask/colorama/ansitowin32.py
FastFlask/colorama/initialise.py
FastFlask/colorama/win32.py
FastFlask/colorama/winterm.py
FastFlask/dataclasses/__init__.py
FastFlask/flask/__init__.py
FastFlask/flask/__main__.py
FastFlask/flask/app.py
FastFlask/flask/blueprints.py
FastFlask/flask/cli.py
FastFlask/flask/config.py
FastFlask/flask/ctx.py
FastFlask/flask/debughelpers.py
FastFlask/flask/globals.py
FastFlask/flask/helpers.py
FastFlask/flask/logging.py
FastFlask/flask/scaffold.py
FastFlask/flask/sessions.py
FastFlask/flask/signals.py
FastFlask/flask/templating.py
FastFlask/flask/testing.py
FastFlask/flask/typing.py
FastFlask/flask/views.py
FastFlask/flask/wrappers.py
FastFlask/flask/json/__init__.py
FastFlask/flask/json/tag.py
FastFlask/importlib_metadata/__init__.py
FastFlask/importlib_metadata/_adapters.py
FastFlask/importlib_metadata/_collections.py
FastFlask/importlib_metadata/_compat.py
FastFlask/importlib_metadata/_functools.py
FastFlask/importlib_metadata/_itertools.py
FastFlask/importlib_metadata/_meta.py
FastFlask/importlib_metadata/_text.py
FastFlask/itsdangerous/__init__.py
FastFlask/itsdangerous/_json.py
FastFlask/itsdangerous/encoding.py
FastFlask/itsdangerous/exc.py
FastFlask/itsdangerous/jws.py
FastFlask/itsdangerous/serializer.py
FastFlask/itsdangerous/signer.py
FastFlask/itsdangerous/timed.py
FastFlask/itsdangerous/url_safe.py
FastFlask/markupsafe/__init__.py
FastFlask/markupsafe/_native.py
FastFlask/werkzeug/__init__.py
FastFlask-1.2.32.dist-info/LICENSE
FastFlask-1.2.32.dist-info/METADATA
FastFlask-1.2.32.dist-info/WHEEL
FastFlask-1.2.32.dist-info/top_level.txt
FastFlask-1.2.32.dist-info/RECORD
